{
    "shape": [
        {
            "label": "pig",
            "boxes": null,
            "points": [
                [
                    426,
                    85
                ],
                [
                    452,
                    75
                ],
                [
                    466,
                    65
                ],
                [
                    491,
                    56
                ],
                [
                    517,
                    60
                ],
                [
                    553,
                    76
                ],
                [
                    582,
                    85
                ],
                [
                    607,
                    90
                ],
                [
                    613,
                    106
                ],
                [
                    631,
                    129
                ],
                [
                    629,
                    145
                ],
                [
                    632,
                    164
                ],
                [
                    619,
                    177
                ],
                [
                    610,
                    175
                ],
                [
                    606,
                    167
                ],
                [
                    602,
                    188
                ],
                [
                    581,
                    187
                ],
                [
                    573,
                    169
                ],
                [
                    556,
                    155
                ],
                [
                    539,
                    148
                ],
                [
                    524,
                    141
                ],
                [
                    516,
                    151
                ],
                [
                    502,
                    141
                ],
                [
                    494,
                    129
                ],
                [
                    481,
                    117
                ],
                [
                    469,
                    118
                ],
                [
                    427,
                    117
                ],
                [
                    407,
                    106
                ]
            ]
        },
        {
            "label": "pig",
            "boxes": null,
            "points": [
                [
                    394,
                    181
                ],
                [
                    417,
                    167
                ],
                [
                    433,
                    161
                ],
                [
                    431,
                    144
                ],
                [
                    416,
                    130
                ],
                [
                    406,
                    134
                ],
                [
                    394,
                    139
                ],
                [
                    375,
                    135
                ],
                [
                    350,
                    135
                ],
                [
                    336,
                    143
                ],
                [
                    323,
                    166
                ],
                [
                    313,
                    181
                ],
                [
                    312,
                    203
                ],
                [
                    312,
                    233
                ],
                [
                    321,
                    257
                ],
                [
                    311,
                    269
                ],
                [
                    307,
                    291
                ],
                [
                    313,
                    306
                ],
                [
                    328,
                    323
                ],
                [
                    342,
                    345
                ],
                [
                    363,
                    336
                ],
                [
                    363,
                    318
                ],
                [
                    369,
                    296
                ],
                [
                    374,
                    272
                ],
                [
                    376,
                    256
                ],
                [
                    382,
                    240
                ],
                [
                    398,
                    233
                ],
                [
                    402,
                    219
                ],
                [
                    391,
                    219
                ],
                [
                    396,
                    202
                ]
            ]
        },
        {
            "label": "pig",
            "boxes": null,
            "points": [
                [
                    374,
                    297
                ],
                [
                    389,
                    303
                ],
                [
                    401,
                    313
                ],
                [
                    429,
                    329
                ],
                [
                    452,
                    338
                ],
                [
                    473,
                    349
                ],
                [
                    486,
                    356
                ],
                [
                    503,
                    366
                ],
                [
                    513,
                    375
                ],
                [
                    528,
                    403
                ],
                [
                    531,
                    430
                ],
                [
                    518,
                    449
                ],
                [
                    498,
                    461
                ],
                [
                    480,
                    477
                ],
                [
                    466,
                    497
                ],
                [
                    440,
                    501
                ],
                [
                    432,
                    490
                ],
                [
                    447,
                    466
                ],
                [
                    456,
                    449
                ],
                [
                    455,
                    435
                ],
                [
                    442,
                    427
                ],
                [
                    424,
                    418
                ],
                [
                    412,
                    396
                ],
                [
                    401,
                    399
                ],
                [
                    382,
                    401
                ],
                [
                    365,
                    380
                ],
                [
                    365,
                    366
                ],
                [
                    359,
                    339
                ],
                [
                    361,
                    312
                ]
            ]
        },
        {
            "label": "pig",
            "boxes": null,
            "points": [
                [
                    444,
                    239
                ],
                [
                    432,
                    233
                ],
                [
                    427,
                    219
                ],
                [
                    410,
                    215
                ],
                [
                    401,
                    236
                ],
                [
                    384,
                    243
                ],
                [
                    379,
                    254
                ],
                [
                    379,
                    275
                ],
                [
                    382,
                    290
                ],
                [
                    394,
                    302
                ],
                [
                    417,
                    324
                ],
                [
                    455,
                    341
                ],
                [
                    482,
                    355
                ],
                [
                    510,
                    371
                ],
                [
                    528,
                    404
                ],
                [
                    540,
                    404
                ],
                [
                    543,
                    378
                ],
                [
                    542,
                    346
                ],
                [
                    528,
                    313
                ],
                [
                    516,
                    295
                ],
                [
                    501,
                    277
                ],
                [
                    475,
                    265
                ],
                [
                    452,
                    255
                ]
            ]
        },
        {
            "label": "pig",
            "boxes": null,
            "points": [
                [
                    521,
                    293
                ],
                [
                    515,
                    271
                ],
                [
                    498,
                    266
                ],
                [
                    481,
                    257
                ],
                [
                    466,
                    232
                ],
                [
                    485,
                    228
                ],
                [
                    501,
                    229
                ],
                [
                    522,
                    225
                ],
                [
                    539,
                    201
                ],
                [
                    561,
                    199
                ],
                [
                    576,
                    217
                ],
                [
                    566,
                    240
                ],
                [
                    582,
                    254
                ],
                [
                    600,
                    272
                ],
                [
                    610,
                    302
                ],
                [
                    628,
                    345
                ],
                [
                    631,
                    365
                ],
                [
                    634,
                    401
                ],
                [
                    637,
                    434
                ],
                [
                    642,
                    466
                ],
                [
                    637,
                    498
                ],
                [
                    622,
                    497
                ],
                [
                    607,
                    486
                ],
                [
                    585,
                    474
                ],
                [
                    545,
                    472
                ],
                [
                    533,
                    433
                ],
                [
                    543,
                    401
                ],
                [
                    548,
                    377
                ],
                [
                    544,
                    343
                ],
                [
                    536,
                    317
                ]
            ]
        },
        {
            "label": "pig",
            "boxes": null,
            "points": [
                [
                    445,
                    444
                ],
                [
                    429,
                    462
                ],
                [
                    412,
                    490
                ],
                [
                    421,
                    498
                ],
                [
                    424,
                    514
                ],
                [
                    433,
                    528
                ],
                [
                    440,
                    556
                ],
                [
                    455,
                    556
                ],
                [
                    484,
                    544
                ],
                [
                    500,
                    544
                ],
                [
                    503,
                    560
                ],
                [
                    492,
                    574
                ],
                [
                    503,
                    592
                ],
                [
                    463,
                    619
                ],
                [
                    464,
                    639
                ],
                [
                    471,
                    667
                ],
                [
                    469,
                    686
                ],
                [
                    450,
                    695
                ],
                [
                    427,
                    680
                ],
                [
                    401,
                    681
                ],
                [
                    390,
                    666
                ],
                [
                    401,
                    650
                ],
                [
                    391,
                    623
                ],
                [
                    380,
                    606
                ],
                [
                    359,
                    583
                ],
                [
                    347,
                    560
                ],
                [
                    344,
                    532
                ],
                [
                    340,
                    498
                ],
                [
                    340,
                    465
                ],
                [
                    356,
                    448
                ],
                [
                    380,
                    445
                ],
                [
                    400,
                    432
                ],
                [
                    423,
                    419
                ],
                [
                    440,
                    427
                ]
            ]
        },
        {
            "label": "pig",
            "boxes": null,
            "points": [
                [
                    328,
                    757
                ],
                [
                    345,
                    741
                ],
                [
                    353,
                    724
                ],
                [
                    371,
                    724
                ],
                [
                    379,
                    745
                ],
                [
                    390,
                    766
                ],
                [
                    391,
                    785
                ],
                [
                    400,
                    787
                ],
                [
                    397,
                    803
                ],
                [
                    389,
                    820
                ],
                [
                    385,
                    840
                ],
                [
                    379,
                    865
                ],
                [
                    375,
                    882
                ],
                [
                    373,
                    904
                ],
                [
                    364,
                    928
                ],
                [
                    365,
                    949
                ],
                [
                    368,
                    969
                ],
                [
                    347,
                    965
                ],
                [
                    329,
                    954
                ],
                [
                    327,
                    927
                ],
                [
                    326,
                    902
                ],
                [
                    329,
                    871
                ],
                [
                    336,
                    846
                ],
                [
                    334,
                    818
                ]
            ]
        },
        {
            "label": "pig",
            "boxes": null,
            "points": [
                [
                    403,
                    778
                ],
                [
                    413,
                    756
                ],
                [
                    422,
                    734
                ],
                [
                    432,
                    759
                ],
                [
                    448,
                    750
                ],
                [
                    465,
                    733
                ],
                [
                    475,
                    749
                ],
                [
                    466,
                    778
                ],
                [
                    465,
                    812
                ],
                [
                    469,
                    825
                ],
                [
                    465,
                    846
                ],
                [
                    453,
                    855
                ],
                [
                    433,
                    853
                ],
                [
                    422,
                    860
                ],
                [
                    428,
                    871
                ],
                [
                    426,
                    896
                ],
                [
                    437,
                    899
                ],
                [
                    448,
                    891
                ],
                [
                    436,
                    915
                ],
                [
                    429,
                    933
                ],
                [
                    426,
                    961
                ],
                [
                    416,
                    982
                ],
                [
                    392,
                    986
                ],
                [
                    375,
                    988
                ],
                [
                    361,
                    982
                ],
                [
                    368,
                    970
                ],
                [
                    365,
                    949
                ],
                [
                    364,
                    924
                ],
                [
                    373,
                    901
                ],
                [
                    381,
                    856
                ],
                [
                    397,
                    803
                ]
            ]
        },
        {
            "label": "pig",
            "boxes": null,
            "points": [
                [
                    466,
                    823
                ],
                [
                    481,
                    791
                ],
                [
                    507,
                    774
                ],
                [
                    513,
                    802
                ],
                [
                    531,
                    806
                ],
                [
                    545,
                    808
                ],
                [
                    547,
                    829
                ],
                [
                    536,
                    843
                ],
                [
                    534,
                    874
                ],
                [
                    533,
                    897
                ],
                [
                    528,
                    922
                ],
                [
                    518,
                    950
                ],
                [
                    505,
                    981
                ],
                [
                    482,
                    1002
                ],
                [
                    470,
                    1022
                ],
                [
                    440,
                    1020
                ],
                [
                    408,
                    1015
                ],
                [
                    382,
                    1013
                ],
                [
                    379,
                    996
                ],
                [
                    395,
                    990
                ],
                [
                    421,
                    975
                ],
                [
                    432,
                    962
                ],
                [
                    434,
                    936
                ],
                [
                    439,
                    914
                ],
                [
                    448,
                    892
                ],
                [
                    436,
                    898
                ],
                [
                    431,
                    898
                ],
                [
                    428,
                    872
                ],
                [
                    423,
                    861
                ],
                [
                    433,
                    855
                ],
                [
                    456,
                    854
                ],
                [
                    468,
                    853
                ]
            ]
        },
        {
            "label": "pig",
            "boxes": null,
            "points": [
                [
                    444,
                    1035
                ],
                [
                    477,
                    1022
                ],
                [
                    510,
                    1004
                ],
                [
                    532,
                    991
                ],
                [
                    555,
                    1001
                ],
                [
                    536,
                    1017
                ],
                [
                    528,
                    1029
                ],
                [
                    547,
                    1035
                ],
                [
                    582,
                    1053
                ],
                [
                    597,
                    1039
                ],
                [
                    616,
                    1012
                ],
                [
                    639,
                    1015
                ],
                [
                    629,
                    1041
                ],
                [
                    642,
                    1055
                ],
                [
                    666,
                    1057
                ],
                [
                    703,
                    1061
                ],
                [
                    731,
                    1069
                ],
                [
                    722,
                    1078
                ],
                [
                    682,
                    1077
                ],
                [
                    637,
                    1077
                ],
                [
                    584,
                    1075
                ],
                [
                    521,
                    1075
                ],
                [
                    480,
                    1075
                ],
                [
                    442,
                    1070
                ],
                [
                    423,
                    1056
                ]
            ]
        },
        {
            "label": "pig",
            "boxes": null,
            "points": [
                [
                    823,
                    56
                ],
                [
                    790,
                    54
                ],
                [
                    764,
                    60
                ],
                [
                    727,
                    65
                ],
                [
                    706,
                    66
                ],
                [
                    707,
                    83
                ],
                [
                    698,
                    92
                ],
                [
                    694,
                    115
                ],
                [
                    710,
                    124
                ],
                [
                    729,
                    127
                ],
                [
                    760,
                    122
                ],
                [
                    781,
                    136
                ],
                [
                    811,
                    141
                ],
                [
                    828,
                    127
                ],
                [
                    855,
                    130
                ],
                [
                    837,
                    157
                ],
                [
                    852,
                    167
                ],
                [
                    871,
                    164
                ],
                [
                    902,
                    157
                ],
                [
                    915,
                    149
                ],
                [
                    953,
                    139
                ],
                [
                    963,
                    125
                ],
                [
                    955,
                    97
                ],
                [
                    936,
                    83
                ],
                [
                    911,
                    70
                ],
                [
                    881,
                    66
                ],
                [
                    849,
                    64
                ]
            ]
        },
        {
            "label": "pig",
            "boxes": null,
            "points": [
                [
                    964,
                    140
                ],
                [
                    996,
                    144
                ],
                [
                    1024,
                    156
                ],
                [
                    1061,
                    167
                ],
                [
                    1077,
                    157
                ],
                [
                    1059,
                    146
                ],
                [
                    1074,
                    144
                ],
                [
                    1103,
                    149
                ],
                [
                    1124,
                    145
                ],
                [
                    1133,
                    130
                ],
                [
                    1149,
                    122
                ],
                [
                    1165,
                    112
                ],
                [
                    1153,
                    97
                ],
                [
                    1116,
                    88
                ],
                [
                    1085,
                    88
                ],
                [
                    1045,
                    78
                ],
                [
                    1018,
                    72
                ],
                [
                    990,
                    82
                ],
                [
                    953,
                    87
                ],
                [
                    961,
                    99
                ],
                [
                    964,
                    125
                ]
            ]
        },
        {
            "label": "pig",
            "boxes": null,
            "points": [
                [
                    1142,
                    140
                ],
                [
                    1166,
                    145
                ],
                [
                    1180,
                    156
                ],
                [
                    1210,
                    177
                ],
                [
                    1233,
                    181
                ],
                [
                    1253,
                    187
                ],
                [
                    1270,
                    193
                ],
                [
                    1287,
                    195
                ],
                [
                    1289,
                    214
                ],
                [
                    1290,
                    234
                ],
                [
                    1306,
                    245
                ],
                [
                    1322,
                    224
                ],
                [
                    1328,
                    201
                ],
                [
                    1345,
                    182
                ],
                [
                    1336,
                    151
                ],
                [
                    1312,
                    136
                ],
                [
                    1280,
                    122
                ],
                [
                    1244,
                    113
                ],
                [
                    1224,
                    106
                ],
                [
                    1221,
                    96
                ],
                [
                    1201,
                    95
                ],
                [
                    1179,
                    99
                ],
                [
                    1165,
                    108
                ],
                [
                    1149,
                    119
                ]
            ]
        },
        {
            "label": "pig",
            "boxes": null,
            "points": [
                [
                    1432,
                    177
                ],
                [
                    1469,
                    191
                ],
                [
                    1486,
                    196
                ],
                [
                    1501,
                    197
                ],
                [
                    1495,
                    222
                ],
                [
                    1496,
                    238
                ],
                [
                    1490,
                    255
                ],
                [
                    1480,
                    259
                ],
                [
                    1470,
                    270
                ],
                [
                    1460,
                    262
                ],
                [
                    1439,
                    243
                ],
                [
                    1418,
                    256
                ],
                [
                    1408,
                    250
                ],
                [
                    1400,
                    229
                ],
                [
                    1377,
                    213
                ],
                [
                    1373,
                    187
                ],
                [
                    1392,
                    180
                ],
                [
                    1411,
                    177
                ]
            ]
        },
        {
            "label": "pig",
            "boxes": null,
            "points": [
                [
                    887,
                    1030
                ],
                [
                    910,
                    1034
                ],
                [
                    934,
                    1028
                ],
                [
                    955,
                    1027
                ],
                [
                    979,
                    1023
                ],
                [
                    997,
                    1022
                ],
                [
                    1017,
                    1011
                ],
                [
                    1012,
                    986
                ],
                [
                    1015,
                    959
                ],
                [
                    1028,
                    964
                ],
                [
                    1048,
                    953
                ],
                [
                    1059,
                    981
                ],
                [
                    1060,
                    1002
                ],
                [
                    1069,
                    1020
                ],
                [
                    1081,
                    1045
                ],
                [
                    1064,
                    1059
                ],
                [
                    1040,
                    1072
                ],
                [
                    1008,
                    1077
                ],
                [
                    982,
                    1078
                ],
                [
                    944,
                    1080
                ],
                [
                    917,
                    1080
                ],
                [
                    894,
                    1078
                ],
                [
                    861,
                    1080
                ],
                [
                    831,
                    1078
                ],
                [
                    786,
                    1077
                ],
                [
                    765,
                    1071
                ],
                [
                    770,
                    1053
                ],
                [
                    801,
                    1054
                ],
                [
                    827,
                    1050
                ],
                [
                    818,
                    1027
                ],
                [
                    829,
                    1013
                ],
                [
                    840,
                    1022
                ],
                [
                    868,
                    1014
                ],
                [
                    891,
                    1015
                ],
                [
                    916,
                    1015
                ]
            ]
        },
        {
            "label": "pig",
            "boxes": null,
            "points": [
                [
                    1187,
                    955
                ],
                [
                    1164,
                    971
                ],
                [
                    1139,
                    974
                ],
                [
                    1128,
                    985
                ],
                [
                    1128,
                    999
                ],
                [
                    1107,
                    1011
                ],
                [
                    1112,
                    1030
                ],
                [
                    1095,
                    1020
                ],
                [
                    1095,
                    1043
                ],
                [
                    1117,
                    1051
                ],
                [
                    1168,
                    1056
                ],
                [
                    1217,
                    1045
                ],
                [
                    1248,
                    1029
                ],
                [
                    1275,
                    1017
                ],
                [
                    1295,
                    1007
                ],
                [
                    1311,
                    991
                ],
                [
                    1291,
                    981
                ],
                [
                    1284,
                    969
                ],
                [
                    1264,
                    970
                ],
                [
                    1252,
                    967
                ],
                [
                    1228,
                    969
                ],
                [
                    1215,
                    978
                ],
                [
                    1194,
                    982
                ],
                [
                    1198,
                    967
                ]
            ]
        },
        {
            "label": "pig",
            "boxes": null,
            "points": [
                [
                    1285,
                    967
                ],
                [
                    1285,
                    951
                ],
                [
                    1302,
                    955
                ],
                [
                    1312,
                    944
                ],
                [
                    1303,
                    913
                ],
                [
                    1329,
                    895
                ],
                [
                    1345,
                    914
                ],
                [
                    1354,
                    927
                ],
                [
                    1363,
                    922
                ],
                [
                    1375,
                    915
                ],
                [
                    1358,
                    897
                ],
                [
                    1374,
                    882
                ],
                [
                    1392,
                    877
                ],
                [
                    1412,
                    896
                ],
                [
                    1429,
                    911
                ],
                [
                    1437,
                    924
                ],
                [
                    1428,
                    948
                ],
                [
                    1413,
                    967
                ],
                [
                    1391,
                    982
                ],
                [
                    1368,
                    990
                ],
                [
                    1368,
                    1001
                ],
                [
                    1343,
                    1006
                ],
                [
                    1322,
                    1002
                ],
                [
                    1308,
                    993
                ],
                [
                    1292,
                    981
                ]
            ]
        },
        {
            "label": "pig",
            "boxes": null,
            "points": [
                [
                    1465,
                    870
                ],
                [
                    1473,
                    854
                ],
                [
                    1454,
                    844
                ],
                [
                    1442,
                    865
                ],
                [
                    1428,
                    882
                ],
                [
                    1423,
                    907
                ],
                [
                    1436,
                    925
                ],
                [
                    1445,
                    935
                ],
                [
                    1463,
                    938
                ],
                [
                    1486,
                    936
                ],
                [
                    1508,
                    920
                ],
                [
                    1529,
                    919
                ],
                [
                    1548,
                    904
                ],
                [
                    1543,
                    896
                ],
                [
                    1555,
                    875
                ],
                [
                    1543,
                    865
                ],
                [
                    1526,
                    870
                ],
                [
                    1501,
                    865
                ],
                [
                    1490,
                    865
                ],
                [
                    1484,
                    864
                ]
            ]
        },
        {
            "label": "pig",
            "boxes": null,
            "points": [
                [
                    1521,
                    802
                ],
                [
                    1494,
                    790
                ],
                [
                    1479,
                    811
                ],
                [
                    1476,
                    827
                ],
                [
                    1479,
                    848
                ],
                [
                    1494,
                    857
                ],
                [
                    1517,
                    866
                ],
                [
                    1542,
                    856
                ],
                [
                    1558,
                    841
                ],
                [
                    1555,
                    824
                ],
                [
                    1552,
                    801
                ],
                [
                    1542,
                    802
                ]
            ]
        },
        {
            "label": "pig",
            "boxes": null,
            "points": [
                [
                    1550,
                    775
                ],
                [
                    1539,
                    771
                ],
                [
                    1529,
                    753
                ],
                [
                    1539,
                    741
                ],
                [
                    1554,
                    724
                ],
                [
                    1574,
                    719
                ],
                [
                    1576,
                    739
                ],
                [
                    1584,
                    766
                ],
                [
                    1589,
                    791
                ],
                [
                    1592,
                    808
                ],
                [
                    1601,
                    814
                ],
                [
                    1590,
                    830
                ],
                [
                    1581,
                    843
                ],
                [
                    1577,
                    848
                ],
                [
                    1566,
                    832
                ],
                [
                    1555,
                    808
                ],
                [
                    1556,
                    788
                ]
            ]
        },
        {
            "label": "pig",
            "boxes": null,
            "points": [
                [
                    1577,
                    722
                ],
                [
                    1585,
                    718
                ],
                [
                    1602,
                    734
                ],
                [
                    1603,
                    762
                ],
                [
                    1610,
                    783
                ],
                [
                    1612,
                    804
                ],
                [
                    1605,
                    818
                ],
                [
                    1594,
                    808
                ],
                [
                    1590,
                    791
                ],
                [
                    1587,
                    764
                ],
                [
                    1575,
                    738
                ]
            ]
        }
    ],
    "imagePath": "pig_7_1590666120_img_1.jpg"
}